htrflow/__init__.py
htrflow/cli.py
htrflow/evaluate.py
htrflow/results.py
htrflow/models/__init__.py
htrflow/models/base_model.py
htrflow/models/download.py
htrflow/models/enums.py
htrflow/models/importer.py
htrflow/models/huggingface/__init__.py
htrflow/models/huggingface/dit.py
htrflow/models/huggingface/donut.py
htrflow/models/huggingface/llava_next.py
htrflow/models/huggingface/mixins.py
htrflow/models/huggingface/trocr.py
htrflow/models/openmmlab/__init__.py
htrflow/models/openmmlab/rtmdet.py
htrflow/models/openmmlab/satrn.py
htrflow/models/openmmlab/utils.py
htrflow/models/teklia/__init__.py
htrflow/models/teklia/pylaia.py
htrflow/models/ultralytics/__init__.py
htrflow/models/ultralytics/yolo.py
htrflow/pipeline/__init__.py
htrflow/pipeline/pipeline.py
htrflow/pipeline/steps.py
htrflow/postprocess/__init__.py
htrflow/postprocess/mask_nms.py
htrflow/postprocess/metrics.py
htrflow/postprocess/reading_order.py
htrflow/postprocess/torch_mask_nms.py
htrflow/postprocess/word_segmentation.py
htrflow/serialization/__init__.py
htrflow/serialization/serialization.py
htrflow/serialization/schemas/alto-4-4.xsd
htrflow/serialization/schemas/pagecontent.xsd
htrflow/serialization/templates/alto
htrflow/serialization/templates/page
htrflow/utils/__init__.py
htrflow/utils/draw.py
htrflow/utils/geometry.py
htrflow/utils/imgproc.py
htrflow/utils/layout.py
htrflow/volume/__init__.py
htrflow/volume/node.py
htrflow/volume/volume.py
htrflow-0.2.6.dist-info/METADATA
htrflow-0.2.6.dist-info/WHEEL
htrflow-0.2.6.dist-info/entry_points.txt
htrflow-0.2.6.dist-info/licenses/LICENSE
htrflow-0.2.6.dist-info/RECORD
