Metadata-Version: 2.4
Name: htrflow
Version: 0.2.6
Summary: htrflow is developed at Riksarkivet's AI-lab as an open-source package to simplify HTR
Project-URL: Documentation, https://ai-riksarkivet.github.io/htrflow
Project-URL: Repository, https://github.com/AI-Riksarkivet/htrflow
Author-email: ai@riksarkivet.se
License:                       EUROPEAN UNION PUBLIC LICENCE v. 1.2
License-File: LICENSE
Keywords: htr,htrflow,ocr
Classifier: Development Status :: 4 - Beta
Classifier: Intended Audience :: Developers
Classifier: Operating System :: OS Independent
Classifier: Programming Language :: Python :: 3.10
Classifier: Topic :: Software Development :: Libraries :: Python Modules
Classifier: Typing :: Typed
Requires-Python: <3.13,>=3.10
Requires-Dist: huggingface-hub[cli]>=0.28.1
Requires-Dist: jinja2>=3.1.5
Requires-Dist: jiwer>=3.0.4
Requires-Dist: numpy
Requires-Dist: opencv-python>=4.11.0.86
Requires-Dist: pagexml-tools>=0.5.0
Requires-Dist: pandas
Requires-Dist: pydantic>=2.10.6
Requires-Dist: rich>=13.7.1
Requires-Dist: tqdm<5,>=4.66.2
Requires-Dist: transformers[torch]>=4.47
Requires-Dist: typer>=0.12.0
Requires-Dist: ultralytics>=8.3.74
Requires-Dist: xmlschema<4,>=3.0.2
Provides-Extra: docs
Requires-Dist: mike>=2.1.1; extra == 'docs'
Requires-Dist: mkdocs-git-revision-date-localized-plugin>=1.2.6; extra == 'docs'
Requires-Dist: mkdocs-jupyter>=0.24.6; extra == 'docs'
Requires-Dist: mkdocs-material>=9.5.10; extra == 'docs'
Requires-Dist: mkdocs-swagger-ui-tag>=0.6.10; extra == 'docs'
Requires-Dist: mkdocs-table-reader-plugin>=2.2.2; extra == 'docs'
Requires-Dist: mkdocstrings[python]>=0.20; extra == 'docs'
Requires-Dist: termynal>=0.12.1; extra == 'docs'
